[{"source":"ZHANG Y","target":"ZHANG H","weight":8},{"source":"LI X","target":"LI J","weight":7},{"source":"LI Y","target":"CHEN Z","weight":6},{"source":"LIU Y","target":"YANG G","weight":6},{"source":"ZHANG Y","target":"ZHANG X","weight":5},{"source":"ZHANG Y","target":"ZHANG Z","weight":5},{"source":"ZHANG Y","target":"LI Z","weight":4},{"source":"LI Y","target":"LI Z","weight":4},{"source":"WANG Y","target":"ZHANG Z","weight":4},{"source":"CHEN Y","target":"CHEN Z","weight":4},{"source":"WANG Y","target":"WANG C","weight":4},{"source":"ZHANG X","target":"ZHANG L","weight":4},{"source":"ZHANG Y","target":"LIU J","weight":4},{"source":"LI X","target":"LIU J","weight":4},{"source":"LI J","target":"CHEN J","weight":4},{"source":"ZHANG H","target":"ZHANG J","weight":4},{"source":"LI J","target":"LI S","weight":4},{"source":"WANG X","target":"YANG Y","weight":4},{"source":"LI Z","target":"YANG G","weight":4},{"source":"CHEN Z","target":"CHEN X","weight":4},{"source":"YANG G","target":"YANG H","weight":4},{"source":"LI X","target":"WANG W","weight":4},{"source":"ZHANG Y","target":"WANG Y","weight":3},{"source":"ZHANG Y","target":"LI X","weight":3},{"source":"WANG Y","target":"LI J","weight":3},{"source":"LI Y","target":"CHEN Y","weight":3},{"source":"WANG Y","target":"ZHANG H","weight":3},{"source":"CHEN Y","target":"ZHANG H","weight":3},{"source":"LI J","target":"LI Z","weight":3},{"source":"WANG X","target":"LI Z","weight":3},{"source":"ZHANG H","target":"LI Z","weight":3},{"source":"WANG Y","target":"ZHANG X","weight":3},{"source":"LI Z","target":"ZHANG X","weight":3},{"source":"WANG Y","target":"WANG Z","weight":3},{"source":"LI J","target":"CHEN Z","weight":3},{"source":"LI Z","target":"CHEN Z","weight":3},{"source":"WANG Z","target":"CHEN Z","weight":3},{"source":"LI X","target":"ZHAO Y","weight":3},{"source":"WANG X","target":"WANG H","weight":3},{"source":"LI J","target":"LIU J","weight":3},{"source":"CHEN Y","target":"LIU J","weight":3},{"source":"LI X","target":"CHEN J","weight":3},{"source":"WANG X","target":"CHEN J","weight":3},{"source":"LI Z","target":"CHEN J","weight":3},{"source":"ZHANG Z","target":"CHEN J","weight":3},{"source":"WANG H","target":"WANG L","weight":3},{"source":"LI X","target":"ZHANG J","weight":3},{"source":"ZHANG X","target":"LIU H","weight":3},{"source":"WANG Z","target":"LIU H","weight":3},{"source":"LI Z","target":"LI S","weight":3},{"source":"LI X","target":"ZHANG S","weight":3},{"source":"LI J","target":"ZHANG S","weight":3},{"source":"ZHANG Z","target":"ZHANG S","weight":3},{"source":"CHEN J","target":"ZHANG S","weight":3},{"source":"LI Y","target":"LI C","weight":3},{"source":"CHEN Z","target":"LI C","weight":3},{"source":"LIU Y","target":"LIU S","weight":3},{"source":"LI S","target":"LIU S","weight":3},{"source":"ZHAO Y","target":"YANG G","weight":3},{"source":"LI X","target":"LI H","weight":3},{"source":"LI Y","target":"CHEN X","weight":3},{"source":"LI Z","target":"YANG H","weight":3},{"source":"LI J","target":"WANG W","weight":3},{"source":"LIU J","target":"WANG W","weight":3},{"source":"CHEN Z","target":"LI Q","weight":3},{"source":"LIU S","target":"LI Q","weight":3},{"source":"ZHANG Y","target":"WANG X","weight":2},{"source":"LI X","target":"WANG X","weight":2},{"source":"LI J","target":"WANG X","weight":2},{"source":"LI X","target":"LI Y","weight":2},{"source":"LI J","target":"LI Y","weight":2},{"source":"ZHANG Y","target":"CHEN Y","weight":2},{"source":"WANG Y","target":"CHEN Y","weight":2},{"source":"LI X","target":"CHEN Y","weight":2},{"source":"WANG X","target":"CHEN Y","weight":2},{"source":"LI Y","target":"ZHANG H","weight":2},{"source":"LI X","target":"LI Z","weight":2},{"source":"CHEN Y","target":"LI Z","weight":2},{"source":"LI X","target":"ZHANG X","weight":2},{"source":"LI Y","target":"ZHANG X","weight":2},{"source":"ZHANG Y","target":"WANG Z","weight":2},{"source":"LI X","target":"WANG Z","weight":2},{"source":"LI Z","target":"WANG Z","weight":2},{"source":"LI J","target":"ZHANG Z","weight":2},{"source":"WANG X","target":"ZHANG Z","weight":2},{"source":"CHEN Y","target":"ZHANG Z","weight":2},{"source":"WANG Y","target":"LIU Y","weight":2},{"source":"CHEN Y","target":"LIU Y","weight":2},{"source":"ZHANG Z","target":"LIU Y","weight":2},{"source":"WANG X","target":"CHEN Z","weight":2},{"source":"ZHANG X","target":"CHEN Z","weight":2},{"source":"ZHANG Z","target":"CHEN Z","weight":2},{"source":"LI Z","target":"ZHAO Y","weight":2},{"source":"ZHANG X","target":"ZHAO Y","weight":2},{"source":"LIU Y","target":"ZHAO Y","weight":2},{"source":"WANG X","target":"WANG C","weight":2},{"source":"CHEN Y","target":"WANG C","weight":2},{"source":"WANG Z","target":"WANG C","weight":2},{"source":"ZHANG Z","target":"WANG C","weight":2},{"source":"ZHAO Y","target":"WANG C","weight":2},{"source":"WANG Y","target":"WANG H","weight":2},{"source":"LI X","target":"WANG H","weight":2},{"source":"ZHANG X","target":"WANG H","weight":2},{"source":"WANG C","target":"WANG H","weight":2},{"source":"ZHANG Y","target":"ZHANG L","weight":2},{"source":"WANG Y","target":"ZHANG L","weight":2},{"source":"LI X","target":"ZHANG L","weight":2},{"source":"CHEN Y","target":"ZHANG L","weight":2},{"source":"ZHANG H","target":"ZHANG L","weight":2},{"source":"CHEN Z","target":"LIU J","weight":2},{"source":"LI Y","target":"CHEN J","weight":2},{"source":"ZHANG L","target":"CHEN J","weight":2},{"source":"ZHAO Y","target":"WANG J","weight":2},{"source":"ZHANG Y","target":"WANG L","weight":2},{"source":"LI Y","target":"WANG L","weight":2},{"source":"ZHANG H","target":"WANG L","weight":2},{"source":"ZHANG Y","target":"ZHANG J","weight":2},{"source":"LI J","target":"ZHANG J","weight":2},{"source":"LIU J","target":"ZHANG J","weight":2},{"source":"WANG X","target":"LIU X","weight":2},{"source":"LI Z","target":"LIU X","weight":2},{"source":"ZHANG Y","target":"LIU H","weight":2},{"source":"WANG Y","target":"LIU H","weight":2},{"source":"CHEN Y","target":"LIU H","weight":2},{"source":"ZHANG Z","target":"LIU H","weight":2},{"source":"WANG Y","target":"LI S","weight":2},{"source":"ZHANG Z","target":"LI S","weight":2},{"source":"ZHANG Y","target":"ZHANG S","weight":2},{"source":"WANG Y","target":"ZHANG S","weight":2},{"source":"WANG L","target":"ZHANG S","weight":2},{"source":"LI Z","target":"LI C","weight":2},{"source":"WANG Z","target":"LI C","weight":2},{"source":"LIU Y","target":"LI C","weight":2},{"source":"WANG J","target":"LI C","weight":2},{"source":"WANG Y","target":"SUN Y","weight":2},{"source":"ZHANG H","target":"SUN Y","weight":2},{"source":"ZHANG J","target":"SUN Y","weight":2},{"source":"WANG Z","target":"LIU Z","weight":2},{"source":"LIU X","target":"LIU Z","weight":2},{"source":"WANG X","target":"LIU S","weight":2},{"source":"ZHANG X","target":"LIU S","weight":2},{"source":"LIU Z","target":"LIU S","weight":2},{"source":"LI X","target":"YANG Y","weight":2},{"source":"CHEN Y","target":"YANG Y","weight":2},{"source":"LI J","target":"LI H","weight":2},{"source":"WANG Y","target":"CHEN X","weight":2},{"source":"CHEN Y","target":"CHEN X","weight":2},{"source":"LIU X","target":"CHEN X","weight":2},{"source":"SUN Y","target":"CHEN X","weight":2},{"source":"ZHANG Y","target":"YANG H","weight":2}]
